[
    {
        "model": "core.quote",
        "pk": 1,
        "fields": {
            "service": 1,
            "labor_fees": "50.00",
            "tax": "5.00",
            "status": "Pending",
            "total_price": "55.00"
        }
    },
    {
        "model": "core.quote",
        "pk": 2,
        "fields": {
            "service": 2,
            "labor_fees": "30.00",
            "tax": "3.00",
            "status": "Pending",
            "total_price": "33.00"
        }
    },
    {
        "model": "core.quote",
        "pk": 3,
        "fields": {
            "service": 3,
            "labor_fees": "70.00",
            "tax": "7.00",
            "status": "Pending",
            "total_price": "77.00"
        }
    },
    {
        "model": "core.quote",
        "pk": 4,
        "fields": {
            "service": 4,
            "labor_fees": "80.00",
            "tax": "8.00",
            "status": "Pending",
            "total_price": "88.00"
        }
    }
]